RepliSage/Replikator.py
RepliSage/__init__.py
RepliSage/args_definition.py
RepliSage/common.py
RepliSage/energy_functions.py
RepliSage/initial_structures.py
RepliSage/md_model.py
RepliSage/network_analysis.py
RepliSage/plots.py
RepliSage/replication_simulator.py
RepliSage/run.py
RepliSage/stochastic_model.py
RepliSage/structure_metrics.py
RepliSage/utils.py
RepliSage/vizualization_tools.py
RepliSage/data/replication_timing_data.parquet
RepliSage/forcefields/classic_sm_ff.xml
pyreplisage-0.2.9.dist-info/licenses/LICENSE
pyreplisage-0.2.9.dist-info/METADATA
pyreplisage-0.2.9.dist-info/WHEEL
pyreplisage-0.2.9.dist-info/entry_points.txt
pyreplisage-0.2.9.dist-info/top_level.txt
pyreplisage-0.2.9.dist-info/RECORD
