Metadata-Version: 2.4
Name: pyRepliSage
Version: 0.2.9
Summary: A stochastic model for the modeling of DNA replication and cell-cycle dynamics.
Home-page: https://github.com/SFGLab/RepliSage
Author: Sebastian Korsak
Author-email: s.korsak@datascience.edu.pl
License: GNU General Public License v3.0
Classifier: Programming Language :: Python :: 3
Classifier: License :: OSI Approved :: GNU General Public License v3 (GPLv3)
Classifier: Operating System :: POSIX :: Linux
Requires-Python: >=3.10
License-File: LICENSE
Requires-Dist: scipy>=1.11.4
Requires-Dist: mdtraj>=1.9.9
Requires-Dist: seaborn>=0.13.0
Requires-Dist: statsmodels>=0.14.0
Requires-Dist: matplotlib>=3.8.2
Requires-Dist: numpy<2.0,>1.2
Requires-Dist: pandas>=2.1.3
Requires-Dist: OpenMM>=8.1.1
Requires-Dist: openmm-cuda>=8.1.1
Requires-Dist: scikit-learn>=1.5.2
Requires-Dist: scikit-image>=0.24.0
Requires-Dist: networkx>=3.4.2
Requires-Dist: numba>=0.60.0
Requires-Dist: hilbertcurve>=2.0.5
Requires-Dist: matplotlib-venn>=1.1.1
Requires-Dist: imageio>=2.36.0
Requires-Dist: imageio-ffmpeg>=0.5.1
Requires-Dist: jupyterlab>=4.2.5
Requires-Dist: jupyter_core>=5.7.2
Requires-Dist: tqdm
Requires-Dist: pyarrow
Requires-Dist: fastparquet
Requires-Dist: pyBigWig>=0.3.19
Dynamic: author
Dynamic: author-email
Dynamic: classifier
Dynamic: description
Dynamic: description-content-type
Dynamic: home-page
Dynamic: license
Dynamic: license-file
Dynamic: requires-dist
Dynamic: requires-python
Dynamic: summary
